aicuflow/__init__.py
aicuflow/__main__.py
aicuflow/baseobject.py
aicuflow/client.py
aicuflow/file.py
aicuflow/flow.py
aicuflow/main.py
aicuflow-0.2.0.dist-info/licenses/LICENSE
aicuflow-0.2.0.dist-info/METADATA
aicuflow-0.2.0.dist-info/WHEEL
aicuflow-0.2.0.dist-info/entry_points.txt
aicuflow-0.2.0.dist-info/top_level.txt
aicuflow-0.2.0.dist-info/RECORD
