Metadata-Version: 2.4
Name: aicuflow
Version: 0.2.0
Summary: use aicuflow in your python apps
Author-email: AICU Developers <finn.glas@aicuflow.com>
License-Expression: MIT
Project-URL: Homepage, https://github.com/AICU-HEALTH/aicuflow-python
Project-URL: Issues, https://github.com/AICU-HEALTH/aicuflow-python/issues
Classifier: Programming Language :: Python :: 3
Classifier: Operating System :: OS Independent
Requires-Python: >=3.9
License-File: LICENSE
Dynamic: license-file
